scadgen/__init__.py
scadgen/scadobj.py
scadgen/scadobj_test.py
scadgen-0.0.2.dist-info/LICENSE
scadgen-0.0.2.dist-info/WHEEL
scadgen-0.0.2.dist-info/METADATA
scadgen-0.0.2.dist-info/RECORD
